pyxorfilter/_xorfilter.abi3.so
pyxorfilter/__init__.py
pyxorfilter/ffibuild.py
pyxorfilter/pyxorfilter.py
pyxorfilter-1.1.2.dist-info/RECORD
pyxorfilter-1.1.2.dist-info/WHEEL
pyxorfilter-1.1.2.dist-info/METADATA
pyxorfilter-1.1.2.dist-info/top_level.txt
pyxorfilter-1.1.2.dist-info/LICENSE
tests/test_fuse16.py
tests/__init__.py
tests/test_xor8.py
tests/test_xor16.py
tests/test_fuse8.py
