Metadata-Version: 2.1
Name: pyxorfilter
Version: 1.1.2
Summary: Python bindings for C implementation of xorfilter
Home-page: https://github.com/glitzflitz/pyxorfilter
Author: Amey Narkhede
Author-email: ameynarkhede02@gmail.com
License: Apache 2.0
Platform: UNKNOWN
Requires-Python: >=3.0
License-File: LICENSE
Requires-Dist: cffi
Requires-Dist: xxhash
